async_privat/__init__.py
async_privat/manager.py
drf_privat/__init__.py
drf_privat/admin.py
drf_privat/apps.py
drf_privat/models.py
drf_privat/serializers.py
drf_privat/sphinx_settings.py
drf_privat/urls.py
drf_privat/views.py
drf_privat/migrations/0001_initial.py
drf_privat/migrations/__init__.py
fastapi_privat/__init__.py
fastapi_privat/crud.py
fastapi_privat/database.py
fastapi_privat/models.py
fastapi_privat/router.py
fastapi_privat/schemas.py
privat_config/__init__.py
privat_config/config.py
privat_config/manager.py
sync_privat/__init__.py
sync_privat/manager.py
python_privatbank_client-0.1.0.dist-info/LICENSE.md
python_privatbank_client-0.1.0.dist-info/METADATA
python_privatbank_client-0.1.0.dist-info/WHEEL
python_privatbank_client-0.1.0.dist-info/top_level.txt
python_privatbank_client-0.1.0.dist-info/RECORD
