Metadata-Version: 2.2
Name: python-privatbank-client
Version: 0.1.0
Summary: This module is designed for quick interaction with the privatbank API.
Home-page: https://github.com/Onix-Systems/python-privatbank-client/tree/v0.1.0
Author: Viacheslav Lisovoi
Author-email: viacheslav.lisovoi@onix-systems.com
Keywords: files speedfiles
Classifier: Programming Language :: Python :: 3.11
Classifier: License :: OSI Approved :: MIT License
Classifier: Operating System :: OS Independent
Requires-Python: >=3.6
License-File: LICENSE.md
Requires-Dist: python-dotenv==1.0.0
Provides-Extra: http
Requires-Dist: requests>=2.25.1; extra == "http"
Provides-Extra: aio
Requires-Dist: aiohttp==3.9.1; extra == "aio"
Provides-Extra: drf
Requires-Dist: Django<5,>=4; extra == "drf"
Requires-Dist: djangorestframework; extra == "drf"
Requires-Dist: requests>=2.25.1; extra == "drf"
Provides-Extra: fastapi
Requires-Dist: fastapi[all]; extra == "fastapi"
Requires-Dist: sqlalchemy; extra == "fastapi"
Requires-Dist: psycopg2; extra == "fastapi"
Requires-Dist: asyncpg; extra == "fastapi"
Provides-Extra: all
Requires-Dist: Django<5,>=4; extra == "all"
Requires-Dist: djangorestframework; extra == "all"
Requires-Dist: requests>=2.25.1; extra == "all"
Requires-Dist: fastapi[all]; extra == "all"
Requires-Dist: aiohttp==3.9.1; extra == "all"
Requires-Dist: sqlalchemy; extra == "all"
Requires-Dist: psycopg2; extra == "all"
Requires-Dist: asyncpg; extra == "all"
Requires-Dist: alembic; extra == "all"
Dynamic: author
Dynamic: author-email
Dynamic: classifier
Dynamic: description
Dynamic: description-content-type
Dynamic: home-page
Dynamic: keywords
Dynamic: provides-extra
Dynamic: requires-dist
Dynamic: requires-python
Dynamic: summary
